rcline/__init__.py
rcline/cat.py
rcline/circle.py
rcline/collide.py
rcline/colors.py
rcline/entity.py
rcline/line.py
rcline/map.py
rcline/polygon.py
rcline-0.6.0.dist-info/licenses/LICENSE
rcline-0.6.0.dist-info/METADATA
rcline-0.6.0.dist-info/WHEEL
rcline-0.6.0.dist-info/top_level.txt
rcline-0.6.0.dist-info/RECORD
