Metadata-Version: 2.4
Name: rcline
Version: 0.6.0
Summary: A 2D simulation package for cat and line interaction with collision detection
Author-email: WallyHao <1276672206@qq.com>
License: Apache
Project-URL: Homepage, https://github.com/waliwuao/rcline
Project-URL: Bug Tracker, https://github.com/waliwuao/rcline/issues
Classifier: Programming Language :: Python :: 3
Classifier: License :: OSI Approved :: MIT License
Classifier: Operating System :: OS Independent
Classifier: Topic :: Scientific/Engineering :: Visualization
Classifier: Topic :: Software Development :: Libraries :: Python Modules
Requires-Python: >=3.8
License-File: LICENSE
Requires-Dist: matplotlib>=3.5.0
Requires-Dist: numpy>=1.21.0
Requires-Dist: keyboard>=0.13.5
Provides-Extra: dev
Requires-Dist: pytest>=7.0.0; extra == "dev"
Requires-Dist: flake8>=4.0.0; extra == "dev"
Requires-Dist: black>=22.0.0; extra == "dev"
Dynamic: license-file
